odoo/addons/hr_payroll_cancel/README.rst
odoo/addons/hr_payroll_cancel/__init__.py
odoo/addons/hr_payroll_cancel/__manifest__.py
odoo/addons/hr_payroll_cancel/i18n/cs_CZ.po
odoo/addons/hr_payroll_cancel/i18n/fr.po
odoo/addons/hr_payroll_cancel/i18n/hr_payroll_cancel.pot
odoo/addons/hr_payroll_cancel/i18n/sl.po
odoo/addons/hr_payroll_cancel/models/__init__.py
odoo/addons/hr_payroll_cancel/models/hr_payroll.py
odoo/addons/hr_payroll_cancel/static/description/icon.png
odoo/addons/hr_payroll_cancel/views/hr_payslip_view.xml
odoo11_addon_hr_payroll_cancel-11.0.1.0.1.dist-info/DESCRIPTION.rst
odoo11_addon_hr_payroll_cancel-11.0.1.0.1.dist-info/METADATA
odoo11_addon_hr_payroll_cancel-11.0.1.0.1.dist-info/RECORD
odoo11_addon_hr_payroll_cancel-11.0.1.0.1.dist-info/WHEEL
odoo11_addon_hr_payroll_cancel-11.0.1.0.1.dist-info/metadata.json
odoo11_addon_hr_payroll_cancel-11.0.1.0.1.dist-info/top_level.txt
