Metadata-Version: 2.0
Name: odoo11-addon-hr-payroll-cancel
Version: 11.0.1.0.1
Summary: Hr Payroll Cancel
Home-page: http://www.vauxoo.com/
Author: Vauxoo, Eficent, Serpent Consulting Services Pvt. Ltd.,Odoo Community Association (OCA)
Author-email: support@odoo-community.org
License: AGPL-3
Platform: UNKNOWN
Classifier: Programming Language :: Python
Classifier: Framework :: Odoo
Classifier: License :: OSI Approved :: GNU Affero General Public License v3
Requires-Python: >=2.7, !=3.0.*, !=3.1.*, !=3.2.*, !=3.3.*, !=3.4.*
Requires-Dist: odoo (<11.1dev,>=11.0a)
